{
  "development": {
    "username": "root",
    "password": null,
    "database": "healoAPI",
    "host": "localhost",
    "dialect": "mysql",
    "logging": false,
    "dialectOptions": {
      "dateStrings": true,
      "typeCast": true,
      "timezone": "+07:00"
    },
    "timezone": "+07:00"
  },
  "test": {
    "username": "root",
    "password": null,
    "database": "healoAPI",
    "host": "localhost",
    "dialect": "mysql"
  },
  "production": {
    "username": "root",
    "password": null,
    "database": "healoAPI",
    "host": "localhost",
    "dialect": "mysql"
  }
}
